{
	"name":"ContactMe",
	"slug":"contactme",
	"version":"4.6",
	"status":"release",
	"include":["ABSPATH.'wp-admin/includes/post.php'"],
	"css_class":"survey",
	"write_only":
	[
		"general",
		"data_collection",
		"graphics",
		"field_definitions",
		"views"
	],
	"force_to_db":true,
	"wordpress":
	{
		"tags":
		[
			"contact",
			"captcha",
			"data collection",
			"survey",
			"poll",
			"quiz"
		],
		"uri":"http://contactme.dcoda.co.uk/",
		"wpslug":"wp-contactme",
		"short_desc":"An Easy to modify Contact Form",
		"stable_tag":"4.6.48",
		"donate_link":"http://contactme.dcoda.co.uk/donate/"
	},
	"classes":
	{
		"form":"contactme_application_form",
		"legacy":"contactme_data_legacy",
		"_load":
		[
			"contactme_application_form",
			"contactme_application_form_fields",
			"contactme_application_form_fields_field",
			"bv48fv_mail",
			"wv48fv_mail",
			"contactme_recaptcha",
			"contactme_gcharts"	,
			"contactme_data_legacy"
		]
	},
	"settings":
	{
		"types":
		{
			"number_captcha":
			{	
				"mandatory_disabled":"disabled",
				"delete_disabled":"",
				"required":"",
				"field":null,
				"fixed_field":null,
				"question_long":"",
				"requires":[],
				"form":{"include":"checked","needs":true,"required":false,"disabled":"disabled"},
				"email":{"include":"","needs":false,"required":false,"disabled":"disabled"},
				"post":{"include":"","needs":false,"required":false,"disabled":"disabled"},
				"results":{"include":"","needs":false,"required":false,"disabled":"disabled"},
				"closed":{"include":"","required":false,"disabled":"disabled"},
				"pending":{"include":"","required":false,"disabled":"disabled"},
				"rss":{"include":"","required":false,"disabled":"disabled"},
				"cookie":{"include":"","required":false,"disabled":"disabled"},
				"private":{"include":"","required":false,"disabled":"disabled"},
				"table":
				{
					"include":"","needs":false,
					"name":"",
					"required":false,"disabled":"disabled"
				},				
				"question":"The sum of <?php echo $this->number1;?> and <?php echo $this->number2;?> is",
				"text":"CAPTCHA: Number",
				"mandatory":"checked",
				"allowed":1
			},
			"textstring":
			{	
				"mandatory_disabled":"disabled",
				"delete_disabled":"",
				"required":"",
				"mandatory":"",
				"field":null,
				"fixed_field":null,
				"options":"",
				"question_long":"",
				"requires":[],
				"form":{"include":"checked","needs":false,"required":false,"disabled":""},
				"email":{"include":"","needs":false,"required":false,"disabled":""},
				"post":{"include":"","needs":false,"required":false,"disabled":""},
				"results":{"include":"","needs":false,"required":false,"disabled":""},
				"closed":{"include":"","needs":false,"required":false,"disabled":""},
				"pending":{"include":"","needs":false,"required":false,"disabled":""},
				"rss":{"include":"","needs":false,"required":false,"disabled":""},
				"cookie":{"include":"","required":false,"disabled":""},
				"private":{"include":"checked","needs":false,"required":false,"disabled":""},
				"table":
				{
					"include":"","needs":false,
					"name":"",
					"required":false,"disabled":"disabled"
				},				
				"text":"Text",
				"allowed":-1
			},
			"recaptcha":
			{
				"mandatory_disabled":"disabled",
				"delete_disabled":"",
				"required":"",
				"field":null,
				"fixed_field":null,
				"allowed":0,
				"question":"",
				"question_long":"",
				"requires":[],
				"form":{"include":"checked","needs":false,"required":false,"disabled":"disabled"},
				"email":{"include":"","needs":false,"required":false,"disabled":"disabled"},
				"post":{"include":"","needs":false,"required":false,"disabled":"disabled"},
				"results":{"include":"","needs":false,"required":false,"disabled":"disabled"},
				"closed":{"include":"","required":false,"disabled":"disabled"},
				"pending":{"include":"","required":false,"disabled":"disabled"},
				"rss":{"include":"","required":false,"disabled":"disabled"},
				"cookie":{"include":"","required":false,"disabled":"disabled"},
				"private":{"include":"","required":false,"disabled":"disabled"},
				"table":
				{
					"include":"","needs":false,
					"name":"",
					"required":false,"disabled":"disabled"
				},				
				"text":"CAPTCHA: ReCAPTCHA",
				"mandatory":"checked",
				"allowed":1
			},
			"cc":
			{
				"mandatory_disabled":"disabled",
				"delete_disabled":"",
				"required":"",
				"mandatory":"",
				"field":null,
				"fixed_field":null,
				"allowed":0,
				"question_long":"",
				"requires":[],
				"form":{"include":"checked","needs":false,"required":false,"disabled":"disabled"},
				"email":{"include":"","needs":true,"required":false,"disabled":""},
				"post":{"include":"","needs":false,"required":false,"disabled":""},
				"results":{"include":"","needs":false,"required":false,"disabled":""},
				"closed":{"include":"","needs":false,"required":false,"disabled":"disabled"},
				"pending":{"include":"","needs":false,"required":false,"disabled":"disabled"},
				"rss":{"include":"","needs":false,"required":false,"disabled":"disabled"},
				"cookie":{"include":"","required":false,"disabled":""},
				"private":{"include":"checked","needs":false,"required":false,"disabled":""},
				"table":
				{
					"include":"","needs":false,
					"name":"",
					"required":false,"disabled":""
				},				
				"question":"Receive Copy?",
				"text":"CC",
				"allowed":1
			},
			"checkbox":
			{
				"mandatory_disabled":"",
				"delete_disabled":"",
				"required":"",
				"mandatory":"",
				"field":null,
				"fixed_field":null,
				"options":"",
				"question":"",
				"question_long":"",
				"requires":[],
				"form":{"include":"checked","needs":false,"required":false,"disabled":"disabled"},
				"email":{"include":"checked","needs":false,"required":false,"disabled":""},
				"post":{"include":"checked","needs":false,"required":false,"disabled":""},
				"results":{"include":"","needs":false,"required":false,"disabled":""},
				"closed":{"include":"","needs":false,"required":false,"disabled":"disabled"},
				"pending":{"include":"","needs":false,"required":false,"disabled":"disabled"},
				"rss":{"include":"","needs":false,"required":false,"disabled":"disabled"},
				"cookie":{"include":"","required":false,"disabled":""},
				"private":{"include":"checked","needs":false,"required":false,"disabled":""},
				"table":
				{
					"include":"checked","needs":false,
					"name":"",
					"required":false,"disabled":""
				},
				"text":"Checkbox",
				"allowed":-1
			},
			"radio":
			{
				"mandatory_disabled":"",
				"delete_disabled":"",
				"required":"",
				"mandatory":"",
				"field":null,
				"fixed_field":null,
				"options":"",
				"question":"",
				"question_long":"",
				"requires":[],
				"form":{"include":"checked","needs":false,"required":false,"disabled":"disabled"},
				"email":{"include":"checked","needs":false,"required":false,"disabled":""},
				"post":{"include":"checked","needs":false,"required":false,"disabled":""},
				"results":{"include":"","needs":false,"required":false,"disabled":""},
				"closed":{"include":"","needs":false,"required":false,"disabled":"disabled"},
				"pending":{"include":"","needs":false,"required":false,"disabled":"disabled"},
				"rss":{"include":"","needs":false,"required":false,"disabled":"disabled"},
				"cookie":{"include":"","required":false,"disabled":""},
				"private":{"include":"checked","needs":false,"required":false,"disabled":""},
				"table":
				{
					"include":"checked","needs":false,
					"name":"",
					"required":false,"disabled":""
				},
				"text":"Radio Button",
				"allowed":-1
			},
			"text":
			{
				"mandatory_disabled":"",
				"delete_disabled":"",
				"required":"",
				"mandatory":"",
				"field":null,
				"fixed_field":null,
				"options":"",
				"question":"",
				"question_long":"",
				"requires":[],
				"form":{"include":"checked","needs":false,"required":false,"disabled":"disabled"},
				"email":{"include":"checked","needs":false,"required":false,"disabled":""},
				"post":{"include":"checked","needs":false,"required":false,"disabled":""},
				"results":{"include":"","needs":false,"required":false,"disabled":""},
				"closed":{"include":"","needs":false,"required":false,"disabled":"disabled"},
				"pending":{"include":"","needs":false,"required":false,"disabled":"disabled"},
				"rss":{"include":"","needs":false,"required":false,"disabled":"disabled"},
				"private":{"include":"checked","needs":false,"required":false,"disabled":""},
				"cookie":{"include":"","required":false,"disabled":""},
				"table":
				{
					"include":"checked","needs":false,
					"name":"",
					"required":false,"disabled":""
				},
				"text":"Text Field",
				"allowed":-1
			},
			"textarea":
			{
				"mandatory_disabled":"",
				"delete_disabled":"",
				"required":"",
				"mandatory":"",
				"field":null,
				"fixed_field":null,
				"question":"",
				"question_long":"",
				"requires":[],
				"form":{"include":"checked","needs":false,"required":false,"disabled":"disabled"},
				"email":{"include":"checked","needs":false,"required":false,"disabled":""},
				"post":{"include":"checked","needs":false,"required":false,"disabled":""},
				"results":{"include":"","needs":false,"required":false,"disabled":""},
				"closed":{"include":"","needs":false,"required":false,"disabled":"disabled"},
				"pending":{"include":"","needs":false,"required":false,"disabled":"disabled"},
				"rss":{"include":"","needs":false,"required":false,"disabled":"disabled"},
				"cookie":{"include":"","required":false,"disabled":""},
				"private":{"include":"checked","required":false,"disabled":""},
				"table":
				{
					"include":"checked","needs":false,
					"name":"",
					"required":false,"disabled":""
				},
				"text":"Text Box",
				"allowed":-1
			},
			"submit":
			{
				"mandatory_disabled":"",
				"delete_disabled":"",
				"mandatory":"",
				"field":null,
				"allowed":0,
				"question_long":"",
				"requires":[],
				"form":{"include":"checked","needs":false,"required":true,"disabled":"disabled"},
				"email":{"include":"","needs":false,"required":false,"disabled":""},
				"post":{"include":"","needs":false,"required":false,"disabled":""},
				"results":{"include":"","needs":false,"required":false,"disabled":""},
				"closed":{"include":"","needs":false,"required":false,"disabled":"disabled"},
				"pending":{"include":"","needs":false,"required":false,"disabled":"disabled"},
				"rss":{"include":"","needs":false,"required":false,"disabled":"disabled"},
				"private":{"include":"","needs":false,"required":false,"disabled":"disabled"},
				"cookie":{"include":"","required":false,"disabled":"disabled"},
				"table":
				{
					"include":"checked","needs":false,
					"name":"",
					"required":false,"disabled":"disabled"
				},
				"required":"checked",
				"text":"Submit",
				"fixed_field":99999,
				"question":"Submit",
				"allowed":1
			},
			"wpuser":
			{
				"mandatory_disabled":"disabled",
				"delete_disabled":"disabled",
				"mandatory":"checked",
				"field":null,
				"allowed":0,
				"question":"",
				"question_long":"",
				"requires":[],
				"form":{"include":"checked","needs":false,"required":false,"disabled":"disabled"},
				"email":{"include":"","needs":false,"required":false,"disabled":""},
				"post":{"include":"","needs":false,"required":false,"disabled":""},
				"results":{"include":"","needs":false,"required":false,"disabled":""},
				"closed":{"include":"","needs":false,"required":false,"disabled":"disabled"},
				"pending":{"include":"","required":false,"disabled":"disabled"},
				"rss":{"include":"","required":false,"disabled":"disabled"},
				"cookie":{"include":"","required":false,"disabled":"disabled"},
				"private":{"include":"","required":false,"disabled":"disabled"},
				"table":
				{
					"include":"checked","needs":false,
					"name":"info[wp_user]",
					"required":true,"disabled":"disabled"
				},				
				"required":"checked",
				"text":"WordPress ID",
				"fixed_field":-2,
				"allowed":0
			},
			"formsent":
			{
				"mandatory_disabled":"disabled",
				"delete_disabled":"disabled",
				"mandatory":"",
				"field":null,
				"allowed":0,
				"question":"",
				"question_long":"",
				"requires":[],
				"form":{"include":"checked","needs":false,"required":false,"disabled":"disabled"},
				"email":{"include":"","needs":false,"required":false,"disabled":""},
				"post":{"include":"","needs":false,"required":false,"disabled":""},
				"results":{"include":"","needs":false,"required":false,"disabled":""},
				"closed":{"include":"","required":false,"disabled":"disabled"},
				"pending":{"include":"","required":false,"disabled":"disabled"},
				"rss":{"include":"","required":false,"disabled":"disabled"},
				"cookie":{"include":"","required":false,"disabled":"disabled"},
				"private":{"include":"","required":false,"disabled":"disabled"},
				"table":
				{
					"include":"checked","needs":false,
					"name":"info[form_sent]",
					"required":true,"disabled":"disabled"
				},				
				"required":"checked",
				"text":"Form Sent Date",
				"fixed_field":99998,
				"allowed":0
			},
			"cookie":
			{
				"mandatory_disabled":"disabled",
				"delete_disabled":"disabled",
				"mandatory":"checked",
				"field":null,
				"allowed":0,
				"question":"",
				"question_long":"",
				"requires":[],
				"form":{"include":"checked","needs":false,"required":true,"disabled":"disabled"},
				"email":{"include":"","needs":false,"required":false,"disabled":"disabled"},
				"post":{"include":"","needs":false,"required":false,"disabled":"disabled"},
				"results":{"include":"checked","needs":false,"required":false,"disabled":"disabled"},
				"closed":{"include":"","needs":false,"required":false,"disabled":"disabled"},
				"pending":{"include":"","needs":false,"required":false,"disabled":"disabled"},
				"rss":{"include":"","required":false,"disabled":"disabled"},
				"cookie":{"include":"checked","required":false,"disabled":"disabled"},
				"private":{"include":"","required":false,"disabled":"disabled"},
				"table":
				{
					"include":"","needs":false,
					"name":"",
					"required":false,"disabled":"disabled"
				},				
				"required":"checked",
				"text":"Browser Cookie",
				"fixed_field":-3,
				"allowed":0
			},
			"results_header":
			{
				"mandatory":"",
				"mandatory_disabled":"disabled",
				"delete_disabled":"disabled",
				"field":null,
				"allowed":0,
				"requires":[],
				"form":{"include":"","needs":false,"required":false,"disabled":"disabled"},
				"email":{"include":"","needs":false,"required":false,"disabled":"disabled","text":""},
				"post":{"include":"","needs":false,"required":false,"disabled":"disabled","text":""},
				"results":{"include":"checked","needs":true,"required":true,"disabled":"disabled","text":""},
				"closed":{"include":"","required":false,"disabled":"disabled"},
				"pending":{"include":"","required":false,"disabled":"disabled"},
				"rss":{"include":"","required":false,"disabled":"disabled"},
				"cookie":{"include":"","required":false,"disabled":"disabled"},
				"private":{"include":"","required":false,"disabled":"disabled"},
				"table":
				{
					"include":"","needs":false,
					"name":"",
					"required":false,
					"disabled":"disabled"
				},				
				"required":"checked",
				"text":"Results Header",
				"fixed_field":-11,
				"allowed":0
			},
			"post_header":
			{
				"mandatory":"",
				"mandatory_disabled":"disabled",
				"delete_disabled":"disabled",
				"field":null,
				"allowed":0,
				"requires":[],
				"form":{"include":"","needs":false,"required":false,"disabled":"disabled"},
				"email":{"include":"","needs":false,"required":false,"disabled":"disabled","text":""},
				"post":{"include":"checked","needs":true,"required":true,"disabled":"disabled","text":"Submitted by <?php echo $this->sender->name;?>"},
				"results":{"include":"","needs":false,"required":false,"disabled":"disabled","text":""},
				"closed":{"include":"","required":false,"disabled":"disabled"},
				"pending":{"include":"","required":false,"disabled":"disabled"},
				"rss":{"include":"","required":false,"disabled":"disabled"},
				"cookie":{"include":"","required":false,"disabled":"disabled"},
				"private":{"include":"","required":false,"disabled":"disabled"},
				"table":
				{
					"include":"","needs":false,
					"name":"",
					"required":false,
					"disabled":"disabled"
				},				
				"required":"checked",
				"text":"Post Header",
				"fixed_field":-10,
				"allowed":0
			},
			"email_header":
			{
				"mandatory":"",
				"mandatory_disabled":"disabled",
				"delete_disabled":"disabled",
				"field":null,
				"allowed":0,
				"requires":[],
				"form":{"include":"","needs":false,"required":false,"disabled":"disabled"},
				"email":{"include":"checked","needs":true,"required":true,"disabled":"disabled","text":"Submitted by <?php echo $this->sender->name;?> <<?php echo $this->sender->email;?>>"},
				"post":{"include":"","needs":false,"required":false,"disabled":"disabled","text":""},
				"results":{"include":"","needs":false,"required":false,"disabled":"disabled","text":""},
				"closed":{"include":"","required":false,"disabled":"disabled"},
				"pending":{"include":"","required":false,"disabled":"disabled"},
				"rss":{"include":"","required":false,"disabled":"disabled"},
				"cookie":{"include":"","required":false,"disabled":"disabled"},
				"private":{"include":"","required":false,"disabled":"disabled"},
				"table":
				{
					"include":"","needs":false,
					"name":"",
					"required":false,
					"disabled":"disabled"
				},				
				"required":"checked",
				"text":"Email Header",
				"fixed_field":-9,
				"allowed":0
			},
			"quiz_header":
			{
				"mandatory":"",
				"mandatory_disabled":"disabled",
				"delete_disabled":"disabled",
				"field":null,
				"allowed":0,
				"requires":[],
				"form":{"include":"","needs":false,"required":false,"disabled":"disabled"},
				"email":{"include":"","needs":false,"required":false,"disabled":"","text":""},
				"post":{"include":"","needs":false,"required":false,"disabled":"","text":""},
				"results":{"include":"checked","needs":true,"required":true,"disabled":"disabled","text":""},
				"quiz":{"text":"You scored <?php echo $this->correct;?> out of a possible <?php echo $this->questions;?>"},
				"closed":{"include":"","required":false,"disabled":"disabled"},
				"pending":{"include":"","required":false,"disabled":"disabled"},
				"rss":{"include":"","required":false,"disabled":"disabled"},
				"cookie":{"include":"","required":false,"disabled":"disabled"},
				"private":{"include":"","required":false,"disabled":"disabled"},
				"table":
				{
					"include":"checked","needs":false,
					"name":"",
					"required":false,
					"disabled":"disabled"
				},				
				"required":"checked",
				"text":"Quiz Score",
				"fixed_field":-8,
				"allowed":0
			},
			"closed_header":
			{
				"mandatory":"",
				"mandatory_disabled":"disabled",
				"delete_disabled":"disabled",
				"field":null,
				"allowed":0,
				"requires":[],
				"form":{"include":"","needs":false,"required":true,"disabled":"disabled"},
				"email":{"include":"","needs":false,"required":false,"disabled":"disabled","text":""},
				"post":{"include":"","needs":false,"required":false,"disabled":"disabled","text":""},
				"results":{"include":"","needs":false,"required":false,"disabled":"disabled","text":""},
				"closed":{"include":"checked","required":false,"disabled":"disabled"},
				"pending":{"include":"","required":false,"disabled":"disabled"},
				"rss":{"include":"","required":false,"disabled":"disabled"},
				"cookie":{"include":"","required":false,"disabled":"disabled"},
				"private":{"include":"","required":false,"disabled":"disabled"},
				"table":
				{
					"include":"","needs":false,
					"name":"",
					"required":false,
					"disabled":"disabled"
				},				
				"required":"checked",
				"text":"Closed Header",
				"fixed_field":-7,
				"allowed":0
			},
			"pending_header":
			{
				"mandatory":"",
				"mandatory_disabled":"disabled",
				"delete_disabled":"disabled",
				"field":null,
				"allowed":0,
				"requires":[],
				"form":{"include":"","needs":false,"required":true,"disabled":"disabled"},
				"email":{"include":"","needs":false,"required":false,"disabled":"disabled","text":""},
				"post":{"include":"","needs":false,"required":false,"disabled":"disabled","text":""},
				"results":{"include":"","needs":false,"required":false,"disabled":"disabled","text":""},
				"closed":{"include":"","required":false,"disabled":"disabled"},
				"pending":{"include":"checked","required":false,"disabled":"disabled"},
				"rss":{"include":"","required":false,"disabled":"disabled"},
				"cookie":{"include":"","required":false,"disabled":"disabled"},
				"private":{"include":"","required":false,"disabled":"disabled"},
				"table":
				{
					"include":"","needs":false,
					"name":"",
					"required":false,
					"disabled":"disabled"
				},				
				"required":"checked",
				"text":"Pending Header",
				"fixed_field":-6,
				"allowed":0
			},
			"rss_header":
			{
				"mandatory":"",
				"mandatory_disabled":"disabled",
				"delete_disabled":"disabled",
				"field":null,
				"allowed":0,
				"requires":[],
				"form":{"include":"","needs":false,"required":true,"disabled":"disabled"},
				"email":{"include":"","needs":false,"required":false,"disabled":"disabled","text":""},
				"post":{"include":"","needs":false,"required":false,"disabled":"disabled","text":""},
				"results":{"include":"","needs":false,"required":false,"disabled":"disabled","text":""},
				"closed":{"include":"","needs":false,"required":false,"disabled":"disabled"},
				"pending":{"include":"","needs":false,"required":false,"disabled":"disabled"},
				"rss":{"include":"checked","required":false,"disabled":"disabled"},
				"cookie":{"include":"","required":false,"disabled":"disabled"},
				"private":{"include":"","required":false,"disabled":"disabled"},
				"table":
				{
					"include":"","needs":false,
					"name":"",
					"required":false,
					"disabled":"disabled"
				},				
				"required":"checked",
				"text":"RSS Header",
				"fixed_field":-5,
				"allowed":0
			},
			"private_footer":
			{
				"mandatory":"",
				"mandatory_disabled":"disabled",
				"delete_disabled":"disabled",
				"field":null,
				"allowed":0,
				"requires":[],
				"form":{"include":"","needs":false,"required":true,"disabled":"disabled"},
				"email":{"include":"","needs":false,"required":false,"disabled":"disabled","text":""},
				"post":{"include":"","needs":false,"required":false,"disabled":"disabled","text":""},
				"results":{"include":"","needs":false,"required":false,"disabled":"disabled","text":""},
				"closed":{"include":"","required":false,"disabled":"disabled"},
				"pending":{"include":"","required":false,"disabled":"disabled"},
				"rss":{"include":"","required":false,"disabled":"disabled"},
				"cookie":{"include":"","required":false,"disabled":"disabled"},
				"private":{"include":"checked","required":false,"disabled":"disabled"},
				"table":
				{
					"include":"","needs":false,
					"name":"",
					"required":false,
					"disabled":"disabled"
				},				
				"required":"checked",
				"text":"Private Footer",
				"fixed_field":100000,
				"allowed":0
			},
			"email_footer":
			{
				"mandatory":"",
				"mandatory_disabled":"disabled",
				"delete_disabled":"disabled",
				"field":null,
				"allowed":0,
				"requires":[],
				"form":{"include":"","needs":false,"required":false,"disabled":"disabled"},
				"email":{"include":"checked","needs":true,"required":true,"disabled":"disabled","text":"--\nThis mail is sent via <?php the_title (); ?> on <?php bloginfo ( 'name' );?> <?php bloginfo ( 'url' );?>"},
				"post":{"include":"","needs":false,"required":false,"disabled":"disabled"},
				"results":{"include":"","needs":false,"required":false,"disabled":"disabled"},
				"closed":{"include":"","required":false,"disabled":"disabled"},
				"pending":{"include":"","required":false,"disabled":"disabled"},
				"rss":{"include":"","required":false,"disabled":"disabled"},
				"cookie":{"include":"","required":false,"disabled":"disabled"},
				"private":{"include":"","required":false,"disabled":"disabled"},
				"table":
				{
					"include":"","needs":false,
					"name":"",
					"required":false,
					"disabled":"disabled"
				},				
				"required":"checked",
				"text":"Email Footer",
				"fixed_field":100001,
				"allowed":0
			},
			"name":
			{
				"mandatory_disabled":"",
				"delete_disabled":"",
				"required":"",
				"mandatory":"",
				"field":null,
				"fixed_field":null,
				"requires":[],
				"form":{"include":"checked","needs":false,"required":false,"disabled":"disabled"},
				"email":{"include":"","needs":false,"required":false,"disabled":""},
				"post":{"include":"","needs":false,"required":false,"disabled":""},
				"results":{"include":"","needs":false,"required":false,"disabled":""},
				"closed":{"include":"","needs":false,"required":false,"disabled":"disabled"},
				"pending":{"include":"","needs":false,"required":false,"disabled":"disabled"},
				"rss":{"include":"","needs":false,"required":false,"disabled":"disabled"},
				"cookie":{"include":"","required":false,"disabled":""},
				"private":{"include":"checked","required":false,"disabled":""},
				"table":
				{
					"include":"checked","needs":false,
					"name":"",
					"required":false,"disabled":""
				},
				"text":"Name",
				"question":"Your Name",
				"allowed":1
			},
			"email":
			{
				"mandatory_disabled":"",
				"delete_disabled":"",
				"field":null,
				"fixed_field":null,
				"question_long":"",
				"requires":[],
				"form":{"include":"checked","needs":false,"required":false,"disabled":"disabled"},
				"email":{"include":"","needs":false,"required":true,"disabled":""},
				"post":{"include":"","needs":false,"required":true,"disabled":""},
				"results":{"include":"","needs":false,"required":false,"disabled":""},
				"cookie":{"include":"","required":false,"disabled":""},
				"private":{"include":"checked","required":false,"disabled":""},
				"table":
				{
					"include":"checked","needs":false,
					"name":"",
					"required":true,"disabled":"disabled"
				},
				"required":"checked",
				"text":"Email Address",
				"mandatory":"checked",
				"question":"Your Email (Required)",
				"closed":{"include":"","required":false,"disabled":"disabled"},
				"pending":{"include":"","required":false,"disabled":"disabled"},
				"rss":{"include":"","required":false,"disabled":"disabled"},
				"allowed":1
			},
			"link":
			{
				"mandatory_disabled":"",
				"delete_disabled":"",
				"required":"",
				"mandatory":"",
				"field":null,
				"fixed_field":null,
				"question":"",
				"question_long":"",
				"requires":[],
				"form":{"include":"checked","needs":false,"required":false,"disabled":"disabled"},
				"email":{"include":"checked","needs":false,"required":false,"disabled":""},
				"post":{"include":"checked","needs":false,"required":false,"disabled":""},
				"results":{"include":"","needs":false,"required":false,"disabled":""},
				"closed":{"include":"","needs":false,"required":false,"disabled":"disabled"},
				"pending":{"include":"","needs":false,"required":false,"disabled":"disabled"},
				"rss":{"include":"","needs":false,"required":false,"disabled":"disabled"},
				"cookie":{"include":"","required":false,"disabled":""},
				"private":{"include":"checked","needs":false,"required":false,"disabled":""},
				"table":
				{
					"include":"checked","needs":false,
					"name":"",
					"required":false,"disabled":""
				},
				"text":"Link",
				"allowed":-1
			},
			"quiz_question":
			{
				"mandatory_disabled":"",
				"delete_disabled":"",
				"required":"",
				"field":null,
				"fixed_field":null,
				"options":"",
				"answer":"",
				"question_long":"",
				"requires":[],
				"form":{"include":"checked","needs":false,"required":false,"disabled":"disabled"},
				"email":{"include":"checked","needs":false,"required":false,"disabled":""},
				"post":{"include":"checked","needs":false,"required":false,"disabled":""},
				"results":{"include":"checked","needs":true,"required":false,"disabled":""},
				"closed":{"include":"","needs":false,"required":false,"disabled":"disabled"},
				"pending":{"include":"","required":false,"disabled":"disabled"},
				"rss":{"include":"","required":false,"disabled":"disabled"},
				"cookie":{"include":"","required":false,"disabled":""},
				"private":{"include":"checked","required":false,"disabled":""},
				"table":
				{
					"include":"checked","needs":false,
					"name":"",
					"required":false,"disabled":""
				},
				"question":null,
				"text":"Quiz Question",
				"mandatory":"checked",
				"allowed":-1
			},
			"poll_question":
			{
				"mandatory_disabled":"",
				"delete_disabled":"",
				"required":"",
				"field":null,
				"fixed_field":null,
				"options":"",
				"question":"",
				"question_long":"",
				"requires":[],
				"form":{"include":"checked","needs":false,"required":false,"disabled":"disabled"},
				"email":{"include":"checked","needs":false,"required":false,"disabled":""},
				"post":{"include":"checked","needs":false,"required":false,"disabled":""},
				"results":{"include":"checked","needs":false,"required":false,"disabled":""},
				"closed":{"include":"checked","needs":false,"required":false,"disabled":""},
				"pending":{"include":"checked","needs":false,"required":false,"disabled":""},
				"rss":{"include":"","required":false,"disabled":"disabled"},
				"cookie":{"include":"checked","required":false,"disabled":""},
				"private":{"include":"checked","required":false,"disabled":""},
				"table":
				{
					"include":"checked","needs":true,
					"name":"",
					"required":false,"disabled":"disabled"
				},
				"text":"Poll Question",
				"mandatory":"checked",
				"allowed":1
			},
			"new":
			{
				"mandatory_disabled":"",
				"delete_disabled":"",
				"mandatory":"",
				"field":null,
				"question":"",
				"question_long":"",
				"requires":[],
				"form":{"include":"","needs":false,"required":true,"disabled":""},
				"email":{"include":"","needs":false,"required":false,"disabled":""},
				"post":{"include":"","needs":false,"required":false,"disabled":""},
				"results":{"include":"","needs":false,"required":false,"disabled":""},
				"closed":{"include":"","needs":false,"required":false,"disabled":"disabled"},
				"pending":{"include":"","needs":false,"required":false,"disabled":"disabled"},
				"rss":{"include":"","needs":false,"required":false,"disabled":"disabled"},
				"private":{"include":"checked","required":false,"disabled":""},
				"table":
				{
					"include":"","needs":false,
					"name":"",
					"required":false,"disabled":""
				},
				"required":"checked",
				"text":"New Field",
				"fixed_field":10000000,
				"allowed":0
			}
		}
	},
	"help_meta":
	{
		"gettingstarted":
		{
			"url":"http://contactme.dcoda.co.uk/help/"
		},
		"forms":
		{
			"url":"http://contactme.dcoda.co.uk/help/forms/"
		},
		"general":
		{
			"url":"http://contactme.dcoda.co.uk/help/editing-forms/general/"
		},
		"data_collection":
		{
			"url":"http://contactme.dcoda.co.uk/help/forms/"
		},
		"fields":
		{
			"url":"http://contactme.dcoda.co.uk/help/editing-forms/fields/"
		}
	}
}